<?xml version="1.0" encoding="UTF-8"?>
<!DOCTYPE suite SYSTEM "http://testng.org/testng-1.0.dtd">
<suite name="Suite">
	<listeners>
		<listener class-name="com.qa.utility.Reporting_FaceBook" />
	</listeners>
	<test name="Test" thread-count="5">
		<parameter name="browser" value="chrome" />
		<parameter name="url" value="https://www.facebook.com/" />
		<classes>
			<class name="com.qa.testscript.TC_FaceBook_001" />
			<class name="com.qa.testscript.TC_FaceBook_003" />
			<class name="com.qa.testscript.TC_FaceBook_002" />
		</classes>
	</test> <!-- Test -->
</suite> <!-- Suite -->
